LICENSE.md
MANIFEST.in
README.md
setup.cfg
setup.py
src/cipher_engine/__init__.py
src/cipher_engine/cipher_engine.py
src/cipher_engine/cli_options.py
src/cipher_engine.egg-info/PKG-INFO
src/cipher_engine.egg-info/SOURCES.txt
src/cipher_engine.egg-info/dependency_links.txt
src/cipher_engine.egg-info/top_level.txt
tests/test_cipher.py