Metadata-Version: 2.1
Name: cipher-engine
Version: 0.4.1
Summary: Versatile cryptographic utility designed for secure encryption and decryption operations. It supports various cryptographic algorithms, implements key derivation functions, and facilitates secure storage using INI/JSON serializations.
Home-page: https://github.com/yousefabuz17/CipherEngine/tree/main
Download-URL: https://github.com/yousefabuz17/CipherEngine.git
Author: Yousef Abuzahrieh
Author-email: yousefzahrieh17@gmail.com
License: Apache Software License
Platform: Windows
Platform: Linux
Platform: MacOS
Classifier: Development Status :: 4 - Beta
Classifier: Intended Audience :: Developers
Classifier: License :: OSI Approved :: Apache Software License
Classifier: Operating System :: OS Independent
Classifier: Programming Language :: Python :: 3
Classifier: Programming Language :: Python :: 3 :: Only
Classifier: Topic :: Security :: Cryptography
Classifier: Topic :: Utilities
License-File: LICENSE.md
